keras_toolkit/__init__.py
keras_toolkit/accelerator.py
keras_toolkit/image.py
keras_toolkit-0.1.0rc6.dist-info/METADATA
keras_toolkit-0.1.0rc6.dist-info/WHEEL
keras_toolkit-0.1.0rc6.dist-info/top_level.txt
keras_toolkit-0.1.0rc6.dist-info/RECORD
