Metadata-Version: 2.1
Name: keras-toolkit
Version: 0.1.0rc6
Summary: A collection of functions to help you easily train and run Tensorflow Keras
Home-page: https://github.com/xhlulu/keras-toolkit
Author: Xing Han Lu
Author-email: github@xinghanlu.com
License: UNKNOWN
Platform: UNKNOWN
Classifier: Programming Language :: Python :: 3
Classifier: License :: OSI Approved :: MIT License
Classifier: Operating System :: OS Independent
Requires-Python: >=3.6
Requires-Dist: tensorflow
Provides-Extra: dev
Requires-Dist: pytest ; extra == 'dev'
Requires-Dist: black ; extra == 'dev'
Requires-Dist: jinja2 ; extra == 'dev'
Requires-Dist: mkdocs ; extra == 'dev'
Requires-Dist: mkdocs-material ; extra == 'dev'
